impo/__init__.py
impo/keys.py
impo-1.1.1.dist-info/METADATA
impo-1.1.1.dist-info/WHEEL
impo-1.1.1.dist-info/licenses/LICENSE.txt
impo-1.1.1.dist-info/RECORD
