Metadata-Version: 2.1
Name: impo
Version: 1.1.1
Summary:  check if imported or if number name
Project-URL: Issues, https://github.com/PyKeys/impo/issues
Project-URL: Twitter, https://twitter.com/py_keys
Project-URL: PythonDiscord, https://discord.gg/python
Author-email: PyKeys <py-keys@hotmail.com>
License-File: LICENSE.txt
Classifier: Operating System :: OS Independent
Classifier: Programming Language :: Python :: 3
